{
  "generatedAt": "2026-06-03T17:03:29.262213+00:00",
  "note": "Historia jest budowana z meczów zapisanych w tym repo. Zakres: od 1 stycznia poprzedniego roku, np. cały 2025 i 2026. Rankingi są z tygodnia meczu, jeśli udało się je pobrać.",
  "historyStartDate": "2025-01-01",
  "player": {
    "key": "aidankim",
    "name": "Aidan Kim",
    "displayName": "A. Kim",
    "playerId": "K0HZ"
  },
  "count": 5,
  "matches": [
    {
      "date": "Mon, 15 September, 2025",
      "dateIso": "2025-09-15",
      "tournamentId": "8281",
      "tournamentYear": "2025",
      "tournamentName": "Columbus",
      "tournamentType": "CH",
      "tournamentDate": "15-21 Sep, 2025",
      "tournamentStartDate": "2025-09-15",
      "tournamentEndDate": "2025-09-21",
      "surface": "",
      "round": "R32",
      "roundLong": "Round of 32",
      "score": "6-2 6-4",
      "matchId": "RES-574B14A8DF",
      "reason": null,
      "playerName": "Aidan Kim",
      "opponentName": "(7/AL)",
      "opponentKey": "7al",
      "result": "L",
      "playerRank": 553,
      "opponentRank": null,
      "rankingDate": "2025-09-15",
      "rankingNote": "historical_week"
    },
    {
      "date": "Mon, 08 September, 2025",
      "dateIso": "2025-09-08",
      "tournamentId": "3011",
      "tournamentYear": "2025",
      "tournamentName": "Winston Salem",
      "tournamentType": "CH",
      "tournamentDate": "8-14 Sep, 2025",
      "tournamentStartDate": "2025-09-08",
      "tournamentEndDate": "2025-09-14",
      "surface": "",
      "round": "R16",
      "roundLong": "Round of 16",
      "score": "6-1 1-6 6-3",
      "matchId": "RES-B88B1DC1D3",
      "reason": null,
      "playerName": "Aidan Kim",
      "opponentName": "Blaise Bicknell",
      "opponentKey": "blaisebicknell",
      "result": "W",
      "playerRank": 606,
      "opponentRank": 599,
      "rankingDate": "2025-09-08",
      "rankingNote": "historical_week"
    },
    {
      "date": "Mon, 08 September, 2025",
      "dateIso": "2025-09-08",
      "tournamentId": "3011",
      "tournamentYear": "2025",
      "tournamentName": "Winston Salem",
      "tournamentType": "CH",
      "tournamentDate": "8-14 Sep, 2025",
      "tournamentStartDate": "2025-09-08",
      "tournamentEndDate": "2025-09-14",
      "surface": "",
      "round": "R32",
      "roundLong": "Round of 32",
      "score": "6-3 6-4",
      "matchId": "RES-8D82F51734",
      "reason": null,
      "playerName": "Aidan Kim",
      "opponentName": "Ryuki Matsuda",
      "opponentKey": "ryukimatsuda",
      "result": "W",
      "playerRank": 606,
      "opponentRank": 471,
      "rankingDate": "2025-09-08",
      "rankingNote": "historical_week"
    },
    {
      "date": "Mon, 04 August, 2025",
      "dateIso": "2025-08-04",
      "tournamentId": "2797",
      "tournamentYear": "2025",
      "tournamentName": "Chicago",
      "tournamentType": "CH",
      "tournamentDate": "4-10 Aug, 2025",
      "tournamentStartDate": "2025-08-04",
      "tournamentEndDate": "2025-08-10",
      "surface": "",
      "round": "Q1",
      "roundLong": "1st Round Qualifying",
      "score": "3-6 6-2 6-3",
      "matchId": "RES-36834B22DA",
      "reason": null,
      "playerName": "Aidan Kim",
      "opponentName": "(6/AL)",
      "opponentKey": "6al",
      "result": "L",
      "playerRank": 616,
      "opponentRank": null,
      "rankingDate": "2025-08-04",
      "rankingNote": "historical_week"
    },
    {
      "date": "",
      "dateIso": "",
      "tournamentId": "2883",
      "tournamentYear": "2025",
      "tournamentName": "Bloomfield Hills",
      "tournamentType": "CH",
      "tournamentDate": "21-27 Jul, 2025",
      "tournamentStartDate": "2025-07-21",
      "tournamentEndDate": "2025-07-27",
      "surface": "",
      "round": "Q2",
      "roundLong": "2nd Round Qualifying",
      "score": "3-6 6-2 7-6(2)",
      "matchId": "RES-7579781BCE",
      "reason": null,
      "playerName": "Aidan Kim",
      "opponentName": "Garrett Johns",
      "opponentKey": "garrettjohns",
      "result": "L",
      "playerRank": null,
      "opponentRank": null,
      "rankingDate": "",
      "rankingNote": "historical_week"
    }
  ]
}