{
  "generatedAt": "2026-05-30T17:34:38.601616+00:00",
  "note": "Historia jest budowana z meczów zapisanych w tym repo. Zakres: od 1 stycznia poprzedniego roku, np. cały 2025 i 2026. Rankingi są z tygodnia meczu, jeśli udało się je pobrać.",
  "historyStartDate": "2025-01-01",
  "player": {
    "key": "alanmagadan",
    "name": "Alan Magadan",
    "displayName": "A. Magadan",
    "playerId": "M0HD"
  },
  "count": 5,
  "matches": [
    {
      "date": "Sat, 21 February, 2026",
      "dateIso": "2026-02-21",
      "tournamentId": "807",
      "tournamentYear": "2026",
      "tournamentName": "Abierto Mexicano Telcel presentado por HSBC",
      "tournamentType": "500",
      "surface": "Hard",
      "round": "Q1",
      "roundLong": "1st Round Qualifying",
      "score": "7-6(0) 6-3",
      "matchId": "RES-BB93539D57",
      "reason": null,
      "playerName": "Alan Magadan",
      "opponentName": "Rinky Hijikata",
      "opponentKey": "rinkyhijikata",
      "result": "L",
      "playerRank": 823,
      "opponentRank": 113,
      "rankingDate": "2026-02-16",
      "rankingNote": "historical_week"
    },
    {
      "date": "",
      "dateIso": "",
      "tournamentId": "7480",
      "tournamentYear": "2025",
      "tournamentName": "Mifel Tennis Open by Telcel Oppo",
      "tournamentType": "250",
      "surface": "Hard",
      "round": "R32",
      "roundLong": "Round of 32",
      "score": "7-6(5) 6-2",
      "matchId": "RES-FF4B917986",
      "reason": null,
      "playerName": "Alan Magadan",
      "opponentName": "Yunchaokete Bu",
      "opponentKey": "yunchaoketebu",
      "result": "L",
      "playerRank": null,
      "opponentRank": null,
      "rankingDate": "",
      "rankingNote": "historical_week"
    },
    {
      "date": "",
      "dateIso": "",
      "tournamentId": "7480",
      "tournamentYear": "2025",
      "tournamentName": "Mifel Tennis Open by Telcel Oppo",
      "tournamentType": "250",
      "surface": "Hard",
      "round": "Q2",
      "roundLong": "2nd Round Qualifying",
      "score": "6-3 6-2",
      "matchId": "RES-75DBCA5596",
      "reason": null,
      "playerName": "Alan Magadan",
      "opponentName": "Mark Lajal",
      "opponentKey": "marklajal",
      "result": "W",
      "playerRank": null,
      "opponentRank": null,
      "rankingDate": "",
      "rankingNote": "historical_week"
    },
    {
      "date": "",
      "dateIso": "",
      "tournamentId": "7480",
      "tournamentYear": "2025",
      "tournamentName": "Mifel Tennis Open by Telcel Oppo",
      "tournamentType": "250",
      "surface": "Hard",
      "round": "Q1",
      "roundLong": "1st Round Qualifying",
      "score": "5-7 6-3 7-6(5)",
      "matchId": "RES-969903B0F7",
      "reason": null,
      "playerName": "Alan Magadan",
      "opponentName": "(7/AL)",
      "opponentKey": "7al",
      "result": "W",
      "playerRank": null,
      "opponentRank": null,
      "rankingDate": "",
      "rankingNote": "historical_week"
    },
    {
      "date": "",
      "dateIso": "",
      "tournamentId": "807",
      "tournamentYear": "2025",
      "tournamentName": "Abierto Mexicano Telcel presentado por HSBC",
      "tournamentType": "500",
      "surface": "Hard",
      "round": "Q1",
      "roundLong": "1st Round Qualifying",
      "score": "6-2 3-6 6-3",
      "matchId": "RES-BE790B0850",
      "reason": null,
      "playerName": "Alan Magadan",
      "opponentName": "Aleksandar Kovacevic",
      "opponentKey": "aleksandarkovacevic",
      "result": "L",
      "playerRank": null,
      "opponentRank": null,
      "rankingDate": "",
      "rankingNote": "historical_week"
    }
  ]
}