{
  "generatedAt": "2026-06-04T04:49:13.685922+00:00",
  "note": "Historia jest budowana z meczów zapisanych w tym repo. Zakres: od 1 stycznia poprzedniego roku, np. cały 2025 i 2026. Rankingi są z tygodnia meczu, jeśli udało się je pobrać.",
  "historyStartDate": "2025-01-01",
  "player": {
    "key": "cezarstefanbentzel",
    "name": "Cezar Stefan Bentzel",
    "displayName": "C. Bentzel",
    "playerId": "B0Y3"
  },
  "count": 2,
  "matches": [
    {
      "date": "Mon, 15 September, 2025",
      "dateIso": "2025-09-15",
      "tournamentId": "3023",
      "tournamentYear": "2025",
      "tournamentName": "Targu Mures 2",
      "tournamentType": "CH",
      "tournamentDate": "16-21 Sep, 2025",
      "tournamentStartDate": "2025-09-16",
      "tournamentEndDate": "2025-09-21",
      "surface": "",
      "round": "R32",
      "roundLong": "Round of 32",
      "score": "6-0 6-3",
      "matchId": "RES-3AD6D7818B",
      "reason": null,
      "playerName": "Cezar Stefan Bentzel",
      "opponentName": "Adrian Boitan",
      "opponentKey": "adrianboitan",
      "result": "L",
      "playerRank": null,
      "opponentRank": 354,
      "rankingDate": "2025-09-15",
      "rankingNote": "historical_week"
    },
    {
      "date": "",
      "dateIso": "",
      "tournamentId": "3021",
      "tournamentYear": "2025",
      "tournamentName": "Targu Mures",
      "tournamentType": "CH",
      "tournamentDate": "8-14 Sep, 2025",
      "tournamentStartDate": "2025-09-08",
      "tournamentEndDate": "2025-09-14",
      "surface": "",
      "round": "Q1",
      "roundLong": "1st Round Qualifying",
      "score": "6-4 7-6(7)",
      "matchId": "RES-759F0F9E41",
      "reason": null,
      "playerName": "Cezar Stefan Bentzel",
      "opponentName": "Jan Jermar",
      "opponentKey": "janjermar",
      "result": "L",
      "playerRank": null,
      "opponentRank": null,
      "rankingDate": "",
      "rankingNote": "historical_week"
    }
  ]
}