{
  "generatedAt": "2026-06-02T04:46:22.664474+00:00",
  "note": "Historia jest budowana z meczów zapisanych w tym repo. Zakres: od 1 stycznia poprzedniego roku, np. cały 2025 i 2026. Rankingi są z tygodnia meczu, jeśli udało się je pobrać.",
  "historyStartDate": "2025-01-01",
  "player": {
    "key": "ronitkarki",
    "name": "Ronit Karki",
    "displayName": "R. Karki",
    "playerId": "K0OY"
  },
  "count": 11,
  "matches": [
    {
      "date": "Mon, 18 May, 2026",
      "dateIso": "2026-05-18",
      "tournamentId": "3109",
      "tournamentYear": "2026",
      "tournamentName": "S M KRISHNA MEMORIAL OPEN",
      "tournamentType": "CH",
      "tournamentDate": "18-23 May, 2026",
      "tournamentStartDate": "2026-05-18",
      "tournamentEndDate": "2026-05-23",
      "surface": "",
      "round": "Q2",
      "roundLong": "2nd Round Qualifying",
      "score": "6-4 6-2",
      "matchId": "RES-E7129F7220",
      "reason": null,
      "playerName": "Ronit Karki",
      "opponentName": "Taiyo Yamanaka",
      "opponentKey": "taiyoyamanaka",
      "result": "L",
      "playerRank": 910,
      "opponentRank": 801,
      "rankingDate": "2026-05-18",
      "rankingNote": "historical_week"
    },
    {
      "date": "Sun, 17 May, 2026",
      "dateIso": "2026-05-17",
      "tournamentId": "3109",
      "tournamentYear": "2026",
      "tournamentName": "S M KRISHNA MEMORIAL OPEN",
      "tournamentType": "CH",
      "tournamentDate": "18-23 May, 2026",
      "tournamentStartDate": "2026-05-18",
      "tournamentEndDate": "2026-05-23",
      "surface": "",
      "round": "Q1",
      "roundLong": "1st Round Qualifying",
      "score": "7-6(4) 6-2",
      "matchId": "RES-8E3E0A13CE",
      "reason": null,
      "playerName": "Ronit Karki",
      "opponentName": "Aryan Lakshmanan",
      "opponentKey": "aryanlakshmanan",
      "result": "W",
      "playerRank": 903,
      "opponentRank": 1516,
      "rankingDate": "2026-05-11",
      "rankingNote": "historical_week"
    },
    {
      "date": "Tue, 12 May, 2026",
      "dateIso": "2026-05-12",
      "tournamentId": "3107",
      "tournamentYear": "2026",
      "tournamentName": "KARNATAKA OPEN",
      "tournamentType": "CH",
      "tournamentDate": "11-16 May, 2026",
      "tournamentStartDate": "2026-05-11",
      "tournamentEndDate": "2026-05-16",
      "surface": "",
      "round": "R32",
      "roundLong": "Round of 32",
      "score": "6-4 7-6(7)",
      "matchId": "RES-EDFE9F8840",
      "reason": null,
      "playerName": "Ronit Karki",
      "opponentName": "Manish Sureshkumar",
      "opponentKey": "manishsureshkumar",
      "result": "L",
      "playerRank": 903,
      "opponentRank": 705,
      "rankingDate": "2026-05-11",
      "rankingNote": "historical_week"
    },
    {
      "date": "Mon, 11 May, 2026",
      "dateIso": "2026-05-11",
      "tournamentId": "3107",
      "tournamentYear": "2026",
      "tournamentName": "KARNATAKA OPEN",
      "tournamentType": "CH",
      "tournamentDate": "11-16 May, 2026",
      "tournamentStartDate": "2026-05-11",
      "tournamentEndDate": "2026-05-16",
      "surface": "",
      "round": "Q2",
      "roundLong": "2nd Round Qualifying",
      "score": "6-2 6-1",
      "matchId": "RES-2FD118530C",
      "reason": null,
      "playerName": "Ronit Karki",
      "opponentName": "Parth Aggarwal",
      "opponentKey": "parthaggarwal",
      "result": "W",
      "playerRank": 903,
      "opponentRank": 1374,
      "rankingDate": "2026-05-11",
      "rankingNote": "historical_week"
    },
    {
      "date": "Sun, 10 May, 2026",
      "dateIso": "2026-05-10",
      "tournamentId": "3107",
      "tournamentYear": "2026",
      "tournamentName": "KARNATAKA OPEN",
      "tournamentType": "CH",
      "tournamentDate": "11-16 May, 2026",
      "tournamentStartDate": "2026-05-11",
      "tournamentEndDate": "2026-05-16",
      "surface": "",
      "round": "Q1",
      "roundLong": "1st Round Qualifying",
      "score": "6-3 6-2",
      "matchId": "RES-691DB33B19",
      "reason": null,
      "playerName": "Ronit Karki",
      "opponentName": "Aradhya Kshitij",
      "opponentKey": "aradhyakshitij",
      "result": "W",
      "playerRank": 962,
      "opponentRank": null,
      "rankingDate": "2026-05-04",
      "rankingNote": "historical_week"
    },
    {
      "date": "Sun, 19 April, 2026",
      "dateIso": "2026-04-19",
      "tournamentId": "5067",
      "tournamentYear": "2026",
      "tournamentName": "Savannah Challenger",
      "tournamentType": "CH",
      "tournamentDate": "20-26 Apr, 2026",
      "tournamentStartDate": "2026-04-20",
      "tournamentEndDate": "2026-04-26",
      "surface": "",
      "round": "Q1",
      "roundLong": "1st Round Qualifying",
      "score": "6-3 6-3",
      "matchId": "RES-328518753C",
      "reason": null,
      "playerName": "Ronit Karki",
      "opponentName": "Tyler Zink",
      "opponentKey": "tylerzink",
      "result": "L",
      "playerRank": 951,
      "opponentRank": 315,
      "rankingDate": "2026-04-13",
      "rankingNote": "historical_week"
    },
    {
      "date": "Mon, 06 April, 2026",
      "dateIso": "2026-04-06",
      "tournamentId": "5069",
      "tournamentYear": "2026",
      "tournamentName": "Elizabeth Moore Sarasota Open",
      "tournamentType": "CH",
      "tournamentDate": "6-12 Apr, 2026",
      "tournamentStartDate": "2026-04-06",
      "tournamentEndDate": "2026-04-12",
      "surface": "",
      "round": "Q2",
      "roundLong": "2nd Round Qualifying",
      "score": "6-4 6-4",
      "matchId": "RES-1D6F363849",
      "reason": null,
      "playerName": "Ronit Karki",
      "opponentName": "Reda Bennani",
      "opponentKey": "redabennani",
      "result": "L",
      "playerRank": 979,
      "opponentRank": 555,
      "rankingDate": "2026-04-06",
      "rankingNote": "historical_week"
    },
    {
      "date": "Sun, 05 April, 2026",
      "dateIso": "2026-04-05",
      "tournamentId": "5069",
      "tournamentYear": "2026",
      "tournamentName": "Elizabeth Moore Sarasota Open",
      "tournamentType": "CH",
      "tournamentDate": "6-12 Apr, 2026",
      "tournamentStartDate": "2026-04-06",
      "tournamentEndDate": "2026-04-12",
      "surface": "",
      "round": "Q1",
      "roundLong": "1st Round Qualifying",
      "score": "2-6 6-2 7-5",
      "matchId": "RES-24DCBFBF9A",
      "reason": null,
      "playerName": "Ronit Karki",
      "opponentName": "Felix Corwin",
      "opponentKey": "felixcorwin",
      "result": "W",
      "playerRank": 1502,
      "opponentRank": 794,
      "rankingDate": "2026-03-30",
      "rankingNote": "historical_week"
    },
    {
      "date": "Tue, 03 March, 2026",
      "dateIso": "2026-03-03",
      "tournamentId": "3067",
      "tournamentYear": "2026",
      "tournamentName": "Fujairah Open",
      "tournamentType": "CH",
      "tournamentDate": "2-8 Mar, 2026",
      "tournamentStartDate": "2026-03-02",
      "tournamentEndDate": "2026-03-08",
      "surface": "",
      "round": "Q2",
      "roundLong": "2nd Round Qualifying",
      "score": "6-3 7-5",
      "matchId": "RES-C167152E3F",
      "reason": null,
      "playerName": "Ronit Karki",
      "opponentName": "Vladyslav Orlov",
      "opponentKey": "vladyslavorlov",
      "result": "L",
      "playerRank": 1607,
      "opponentRank": 516,
      "rankingDate": "2026-03-02",
      "rankingNote": "historical_week"
    },
    {
      "date": "Mon, 02 March, 2026",
      "dateIso": "2026-03-02",
      "tournamentId": "3067",
      "tournamentYear": "2026",
      "tournamentName": "Fujairah Open",
      "tournamentType": "CH",
      "tournamentDate": "2-8 Mar, 2026",
      "tournamentStartDate": "2026-03-02",
      "tournamentEndDate": "2026-03-08",
      "surface": "",
      "round": "Q1",
      "roundLong": "1st Round Qualifying",
      "score": "7-5 6-1",
      "matchId": "RES-6553031A58",
      "reason": null,
      "playerName": "Ronit Karki",
      "opponentName": "Francis Casey Alcantara",
      "opponentKey": "franciscaseyalcantara",
      "result": "W",
      "playerRank": 1607,
      "opponentRank": null,
      "rankingDate": "2026-03-02",
      "rankingNote": "historical_week"
    },
    {
      "date": "Mon, 27 October, 2025",
      "dateIso": "2025-10-27",
      "tournamentId": "6055",
      "tournamentYear": "2025",
      "tournamentName": "Charlottesville",
      "tournamentType": "CH",
      "tournamentDate": "27 Oct - 2 Nov, 2025",
      "tournamentStartDate": "2025-10-27",
      "tournamentEndDate": "2025-11-02",
      "surface": "",
      "round": "R32",
      "roundLong": "Round of 32",
      "score": "6-3 7-5",
      "matchId": "RES-C1153DCB56",
      "reason": null,
      "playerName": "Ronit Karki",
      "opponentName": "Johannus Monday",
      "opponentKey": "johannusmonday",
      "result": "L",
      "playerRank": null,
      "opponentRank": 212,
      "rankingDate": "2025-10-27",
      "rankingNote": "historical_week"
    }
  ]
}