{
  "generatedAt": "2026-06-11T13:20:29.569369+00:00",
  "note": "Historia jest budowana z meczów zapisanych w tym repo. Zakres: od 1 stycznia poprzedniego roku, np. cały 2025 i 2026. Rankingi są z tygodnia meczu, jeśli udało się je pobrać.",
  "historyStartDate": "2025-01-01",
  "player": {
    "key": "samirhamzareguig",
    "name": "Samir Hamza Reguig",
    "displayName": "Samir Hamza Reguig",
    "playerId": ""
  },
  "count": 3,
  "matches": [
    {
      "date": "Thu, 23 April, 2026",
      "dateIso": "2026-04-23",
      "tournamentId": "2995",
      "tournamentYear": "2026",
      "tournamentName": "Cote d'Ivoire Open 1",
      "tournamentType": "CH",
      "tournamentDate": "20 - 26 April, 2026",
      "tournamentStartDate": "",
      "tournamentEndDate": "",
      "surface": "Hard",
      "round": "R16",
      "roundLong": "Round of 16",
      "score": "6-0 6-4",
      "matchId": "RES-B94F2F0D48",
      "reason": null,
      "playerName": "Samir Hamza Reguig",
      "opponentName": "Hamish Stewart",
      "opponentKey": "hamishstewart",
      "result": "L",
      "playerRank": 852,
      "opponentRank": 391,
      "rankingDate": "2026-04-20",
      "rankingNote": "historical_week"
    },
    {
      "date": "Wed, 22 April, 2026",
      "dateIso": "2026-04-22",
      "tournamentId": "2995",
      "tournamentYear": "2026",
      "tournamentName": "Cote d'Ivoire Open 1",
      "tournamentType": "CH",
      "tournamentDate": "20 - 26 April, 2026",
      "tournamentStartDate": "",
      "tournamentEndDate": "",
      "surface": "Hard",
      "round": "R32",
      "roundLong": "Round of 32",
      "score": "6-4 6-1",
      "matchId": "RES-0CDFC5FEFC",
      "reason": null,
      "playerName": "Samir Hamza Reguig",
      "opponentName": "Oscar Weightman",
      "opponentKey": "oscarweightman",
      "result": "W",
      "playerRank": 852,
      "opponentRank": 776,
      "rankingDate": "2026-04-20",
      "rankingNote": "historical_week"
    },
    {
      "date": "Mon, 20 April, 2026",
      "dateIso": "2026-04-20",
      "tournamentId": "2995",
      "tournamentYear": "2026",
      "tournamentName": "Cote d'Ivoire Open 1",
      "tournamentType": "CH",
      "tournamentDate": "20 - 26 April, 2026",
      "tournamentStartDate": "",
      "tournamentEndDate": "",
      "surface": "Hard",
      "round": "Q2",
      "roundLong": "2nd Round Qualifying",
      "score": "7-5 6-3",
      "matchId": "RES-8CB4D50D8C",
      "reason": null,
      "playerName": "Samir Hamza Reguig",
      "opponentName": "Daniel Adeleye",
      "opponentKey": "danieladeleye",
      "result": "W",
      "playerRank": 852,
      "opponentRank": null,
      "rankingDate": "2026-04-20",
      "rankingNote": "historical_week"
    }
  ]
}