{
  "generatedAt": "2026-06-07T19:41:52.320972+00:00",
  "note": "Historia jest budowana z meczów zapisanych w tym repo. Zakres: od 1 stycznia poprzedniego roku, np. cały 2025 i 2026. Rankingi są z tygodnia meczu, jeśli udało się je pobrać.",
  "historyStartDate": "2025-01-01",
  "player": {
    "key": "xiaofeiwang",
    "name": "Xiaofei Wang",
    "displayName": "X. Wang",
    "playerId": "W0B3"
  },
  "count": 6,
  "matches": [
    {
      "date": "Mon, 13 October, 2025",
      "dateIso": "2025-10-13",
      "tournamentId": "3027",
      "tournamentYear": "2025",
      "tournamentName": "Shenzhen (Futian)",
      "tournamentType": "CH",
      "tournamentDate": "13-19 Oct, 2025",
      "tournamentStartDate": "2025-10-13",
      "tournamentEndDate": "2025-10-19",
      "surface": "",
      "round": "R32",
      "roundLong": "Round of 32",
      "score": "6-1 6-2",
      "matchId": "RES-A6B01C6C1D",
      "reason": null,
      "playerName": "Xiaofei Wang",
      "opponentName": "Yi Zhou",
      "opponentKey": "yizhou",
      "result": "L",
      "playerRank": 885,
      "opponentRank": 327,
      "rankingDate": "2025-10-13",
      "rankingNote": "historical_week"
    },
    {
      "date": "Mon, 13 October, 2025",
      "dateIso": "2025-10-13",
      "tournamentId": "3027",
      "tournamentYear": "2025",
      "tournamentName": "Shenzhen (Futian)",
      "tournamentType": "CH",
      "tournamentDate": "13-19 Oct, 2025",
      "tournamentStartDate": "2025-10-13",
      "tournamentEndDate": "2025-10-19",
      "surface": "",
      "round": "Q2",
      "roundLong": "2nd Round Qualifying",
      "score": "6-4 3-6 6-3",
      "matchId": "RES-4477D27846",
      "reason": null,
      "playerName": "Xiaofei Wang",
      "opponentName": "Tsung-Hao Huang",
      "opponentKey": "tsunghaohuang",
      "result": "W",
      "playerRank": 885,
      "opponentRank": 487,
      "rankingDate": "2025-10-13",
      "rankingNote": "historical_week"
    },
    {
      "date": "Mon, 13 October, 2025",
      "dateIso": "2025-10-13",
      "tournamentId": "3027",
      "tournamentYear": "2025",
      "tournamentName": "Shenzhen (Futian)",
      "tournamentType": "CH",
      "tournamentDate": "13-19 Oct, 2025",
      "tournamentStartDate": "2025-10-13",
      "tournamentEndDate": "2025-10-19",
      "surface": "",
      "round": "Q1",
      "roundLong": "1st Round Qualifying",
      "score": "6-3 6-3",
      "matchId": "RES-714E1BE348",
      "reason": null,
      "playerName": "Xiaofei Wang",
      "opponentName": "Linang Xiao",
      "opponentKey": "linangxiao",
      "result": "W",
      "playerRank": 885,
      "opponentRank": 688,
      "rankingDate": "2025-10-13",
      "rankingNote": "historical_week"
    },
    {
      "date": "Mon, 06 October, 2025",
      "dateIso": "2025-10-06",
      "tournamentId": "7746",
      "tournamentYear": "2025",
      "tournamentName": "Jinan",
      "tournamentType": "CH",
      "tournamentDate": "6-12 Oct, 2025",
      "tournamentStartDate": "2025-10-06",
      "tournamentEndDate": "2025-10-12",
      "surface": "",
      "round": "Q2",
      "roundLong": "2nd Round Qualifying",
      "score": "6-4 6-2",
      "matchId": "RES-D4B47CC372",
      "reason": null,
      "playerName": "Xiaofei Wang",
      "opponentName": "Maxim Zhukov",
      "opponentKey": "maximzhukov",
      "result": "L",
      "playerRank": 847,
      "opponentRank": 511,
      "rankingDate": "2025-10-06",
      "rankingNote": "historical_week"
    },
    {
      "date": "Mon, 06 October, 2025",
      "dateIso": "2025-10-06",
      "tournamentId": "7746",
      "tournamentYear": "2025",
      "tournamentName": "Jinan",
      "tournamentType": "CH",
      "tournamentDate": "6-12 Oct, 2025",
      "tournamentStartDate": "2025-10-06",
      "tournamentEndDate": "2025-10-12",
      "surface": "",
      "round": "Q1",
      "roundLong": "1st Round Qualifying",
      "score": "6-2 4-6 6-1",
      "matchId": "RES-D6F944C3F3",
      "reason": null,
      "playerName": "Xiaofei Wang",
      "opponentName": "Hyeon Chung",
      "opponentKey": "hyeonchung",
      "result": "W",
      "playerRank": 847,
      "opponentRank": 519,
      "rankingDate": "2025-10-06",
      "rankingNote": "historical_week"
    },
    {
      "date": "Mon, 22 September, 2025",
      "dateIso": "2025-09-22",
      "tournamentId": "3013",
      "tournamentYear": "2025",
      "tournamentName": "Jingshan",
      "tournamentType": "CH",
      "tournamentDate": "22-28 Sep, 2025",
      "tournamentStartDate": "2025-09-22",
      "tournamentEndDate": "2025-09-28",
      "surface": "",
      "round": "Q1",
      "roundLong": "1st Round Qualifying",
      "score": "6-3 6-2",
      "matchId": "RES-BF15C92AB0",
      "reason": null,
      "playerName": "Xiaofei Wang",
      "opponentName": "Marat Sharipov",
      "opponentKey": "maratsharipov",
      "result": "L",
      "playerRank": 966,
      "opponentRank": 283,
      "rankingDate": "2025-09-22",
      "rankingNote": "historical_week"
    }
  ]
}